yahya_bnoun/__init__.py
yahya_bnoun/yahya.py
yahya_bnoun-0.0.1.dist-info/LICENSE
yahya_bnoun-0.0.1.dist-info/METADATA
yahya_bnoun-0.0.1.dist-info/WHEEL
yahya_bnoun-0.0.1.dist-info/top_level.txt
yahya_bnoun-0.0.1.dist-info/RECORD
