Metadata-Version: 2.1
Name: yahya-bnoun
Version: 0.0.1
Summary: For generating yahya bnoun art
Home-page: https://github.com/yahyabnoun/yahya_bnoun
Author: yahya bnoun
Author-email: yahyaiko22@gmail.com
License: UNKNOWN
Platform: UNKNOWN
Classifier: Programming Language :: Python :: 3
Classifier: License :: OSI Approved :: MIT License
Classifier: Operating System :: OS Independent
Requires-Python: >=3.7
License-File: LICENSE
